stacksplit/__init__.py
stacksplit/__version__.py
stacksplit/core.py
stacksplit-0.0.0.dist-info/AUTHORS.md
stacksplit-0.0.0.dist-info/LICENSE
stacksplit-0.0.0.dist-info/METADATA
stacksplit-0.0.0.dist-info/WHEEL
stacksplit-0.0.0.dist-info/top_level.txt
stacksplit-0.0.0.dist-info/RECORD
