Metadata-Version: 2.1
Name: stacksplit
Version: 0.0.0
Summary: A simple Python library to generate all combinations of possible splits for a stack with given height.
Home-page: https://gitlab.com/felixwallner/stacksplit
Author: Felix Wallner
Author-email: felix.wallner@protonmail.com
License: MIT
Keywords: stack,split,partition,combinations,NIM,Laskers-NIM,gametheorie,coins,sum
Platform: UNKNOWN
Classifier: License :: OSI Approved :: MIT License
Classifier: Programming Language :: Python
Classifier: Programming Language :: Python :: 3
Classifier: Programming Language :: Python :: 3.4
Classifier: Programming Language :: Python :: 3.5
Classifier: Programming Language :: Python :: 3.6
Classifier: Programming Language :: Python :: 3.7
Requires-Python: >=3.4.0
